[
  {
    "idx": 474,
    "genre": 4,
    "q": "受水槽の「揚水ポンプ」の役割はどれか？",
    "o": [
      "受水槽の水を高置水槽や各階に送水する",
      "消火設備の配管に加圧して消火水を供給する",
      "建物外周の排水溝から雨水を排出する",
      "地下ピットに溜まった排水を汲み上げる"
    ],
    "a": 0
  },
  {
    "idx": 482,
    "genre": 4,
    "q": "受水槽の「水位制御方式」のうち、電極棒式の特徴はどれか？",
    "o": [
      "赤外線センサーで水面を検知して水位を制御する",
      "水の電気伝導性を利用して水位を検知する",
      "超音波を反射させて水面までの距離を測定する",
      "フロートの浮力を利用して機械的に動作する"
    ],
    "a": 1
  },
  {
    "idx": 483,
    "genre": 4,
    "q": "受水槽の「フロートスイッチ」の動作原理はどれか？",
    "o": [
      "水温の変化を感知してスイッチを作動させる",
      "配管内の圧力変化を検知して信号を送る",
      "浮き球の上下動でスイッチを切り替える",
      "水の電気伝導性を利用して通電状態を変化させる"
    ],
    "a": 2
  },
  {
    "idx": 490,
    "genre": 4,
    "q": "受水槽の点検で「水位の異常な上昇」が見られた場合の原因はどれか？",
    "o": [
      "給水本管の断水により供給が停止した状態",
      "電極棒の断線により減水信号が発報した状態",
      "ボールタップの閉止不良により給水が止まらない状態",
      "水槽本体の亀裂により漏水が発生した状態"
    ],
    "a": 2
  },
  {
    "idx": 507,
    "genre": 4,
    "q": "受水槽の「ポンプ直送方式」の特徴はどれか？",
    "o": [
      "受水槽を使わず手動で各階に給水する方式",
      "受水槽の水を高置水槽に揚水してから自然流下で給水する方式",
      "受水槽から加圧ポンプで各階に直接給水する方式で高置水槽が不要",
      "水道本管の圧力をそのまま利用して各階に直接給水する方式"
    ],
    "a": 2
  },
  {
    "idx": 513,
    "genre": 4,
    "q": "受水槽の「水位制御盤」の役割はどれか？",
    "o": [
      "残留塩素濃度を常時測定して水質を自動管理する",
      "配管内の水圧を設定値に維持するよう減圧弁を制御する",
      "給水温度を監視して温水器の出力を調整する",
      "電極棒やフロートスイッチの信号を受けてポンプの発停や警報を制御する"
    ],
    "a": 3
  },
  {
    "idx": 532,
    "genre": 4,
    "q": "受水槽の「自動制御盤」が故障した場合のリスクはどれか？",
    "o": [
      "貯湯温度が設定値から外れて給湯品質が低下する",
      "水質検査の自動記録が停止して記録が取れなくなる",
      "ポンプの制御不能により満水・減水・断水等の重大トラブルが発生する",
      "排水管の通気が不十分になり封水が破られる"
    ],
    "a": 2
  },
  {
    "idx": 538,
    "genre": 4,
    "q": "受水槽の「地震後の点検」で確認すべき項目はどれか？",
    "o": [
      "受水槽内の残留塩素値と水質の変化",
      "本体の亀裂・配管の破損・架台のずれ・漏水の有無",
      "マンホール蓋の塗装剥がれと再塗装の要否",
      "制御盤内のブレーカー定格容量の適正性"
    ],
    "a": 1
  },
  {
    "idx": 539,
    "genre": 4,
    "q": "受水槽の「電極棒の清掃」が必要な理由はどれか？",
    "o": [
      "電極棒の外観を美しく保ち定期点検時の写真記録に備えるため",
      "電極棒の表面に付着した酸化膜が導電性を高めすぎるのを防ぐため",
      "電極棒の重量増加により支持金具が破損するのを防止するため",
      "スケールや汚れの付着で誤検知を起こし水位制御が正常に機能しなくなるため"
    ],
    "a": 3
  },
  {
    "idx": 544,
    "genre": 4,
    "q": "受水槽の「揚水ポンプの交互運転」の目的はどれか？",
    "o": [
      "ポンプの運転音を変化させて騒音を軽減する",
      "ポンプの吐出圧力を交互に変えて水圧を安定させる",
      "2台のポンプを交互に使用して摩耗を均等化し寿命を延ばす",
      "水槽内の水を攪拌して残留塩素の均一化を図る"
    ],
    "a": 2
  },
  {
    "idx": 548,
    "genre": 4,
    "q": "受水槽の「増圧ポンプ」の定期点検項目はどれか？",
    "o": [
      "振動・騒音・電流値・圧力・漏水の有無",
      "ポンプ本体の塗装状態と製造銘板の読み取り確認",
      "ポンプ室の照明器具の点灯状態と換気扇の動作",
      "ポンプの基礎コンクリートの含水率と強度測定"
    ],
    "a": 0
  },
  {
    "idx": 554,
    "genre": 4,
    "q": "受水槽の「給水ポンプのインバーター制御」の利点はどれか？",
    "o": [
      "配管口径を自動的に変更して流量を調整する",
      "給水温度を一定に保ちレジオネラ菌の繁殖を抑制する",
      "ポンプの起動回数を減らし電極棒の消耗を抑える",
      "使用水量に応じてポンプ回転数を制御し省エネ・低騒音・水圧安定を実現する"
    ],
    "a": 3
  },
  {
    "idx": 577,
    "genre": 4,
    "q": "受水槽の「点検記録」に記載すべき項目はどれか？",
    "o": [
      "点検当日の天気と気温のみを簡潔に記録する",
      "建物の管理費用と修繕積立金の残高を記録する",
      "近隣建物の給水方式と水槽設置状況を記録する",
      "点検日時・点検者・点検項目・結果・残留塩素値・異常の有無を記録する"
    ],
    "a": 3
  },
  {
    "idx": 590,
    "genre": 4,
    "q": "受水槽の「揚水管」に設ける弁類はどれか？",
    "o": [
      "仕切弁・逆止弁・フレキシブルジョイント等を設ける",
      "排水弁のみを管末に設置して水抜きに使用する",
      "ストレーナーのみを吸込側に設置して異物を除去する",
      "安全弁のみを吐出側に設置して過圧を防止する"
    ],
    "a": 0
  },
  {
    "idx": 591,
    "genre": 4,
    "q": "受水槽の「加圧給水ポンプユニット」の特徴はどれか？",
    "o": [
      "手動操作専用で自動制御機能を持たない据置型の装置",
      "消火設備専用に設計された耐圧型のポンプ装置",
      "排水専用に設計された水中ポンプと制御盤のセット",
      "ポンプ・制御盤・圧力タンク等が一体化されたユニット型給水装置"
    ],
    "a": 3
  },
  {
    "idx": 597,
    "genre": 4,
    "q": "受水槽の「ポンプの空転防止」のための安全装置はどれか？",
    "o": [
      "残留塩素計による水質監視装置",
      "減水検知電極による自動停止機能",
      "管内流量を計測する電磁式流量計",
      "水温上昇を感知するサーミスタ温度計"
    ],
    "a": 1
  },
  {
    "idx": 611,
    "genre": 4,
    "q": "受水槽の「チェックリスト方式の日常点検」で確認する項目はどれか？",
    "o": [
      "ポンプの製造メーカーと型番の変更履歴",
      "マンホール蓋の施錠・防虫網の状態・水槽周辺の清潔さ・異臭の有無・残留塩素",
      "建物全体の外観と敷地内の植栽の状態",
      "配管の保温材の色と材質の適合性"
    ],
    "a": 1
  },
  {
    "idx": 615,
    "genre": 4,
    "q": "揚水ポンプの「異常音」が発生した場合に疑うべき原因はどれか？",
    "o": [
      "配管の保温材が劣化して露出している状態",
      "ポンプの定格出力に対して負荷が小さすぎる状態",
      "軸受の摩耗・キャビテーション・インペラの損傷",
      "制御盤内のブレーカーが定格容量を超えている状態"
    ],
    "a": 2
  },
  {
    "idx": 616,
    "genre": 4,
    "q": "揚水ポンプの「グランドパッキン」からの漏水はどの程度が正常か？",
    "o": [
      "完全に締め付けて全く漏れない状態が正常",
      "毎分数滴程度の漏れは冷却・潤滑のために正常",
      "漏水量に関わらず漏れがあれば直ちに交換が必要",
      "毎分1リットル以上の連続的な流出が正常な範囲"
    ],
    "a": 1
  },
  {
    "idx": 617,
    "genre": 4,
    "q": "揚水ポンプの「メカニカルシール」の特徴はどれか？",
    "o": [
      "グランドパッキンと同じ構造で定期的な増し締めが必要となる",
      "配管同士を接続するフランジ型の継手部品として使用される",
      "グランドパッキンより漏水が少なくメンテナンスフリーに近い軸封方式",
      "ポンプ本体の外殻を構成する耐圧ケーシングの一種"
    ],
    "a": 2
  },
  {
    "idx": 618,
    "genre": 4,
    "q": "揚水ポンプの「定期点検」で確認すべき項目はどれか？",
    "o": [
      "ポンプの製造メーカーと製造年月日の照合",
      "ポンプ本体の塗装状態と外観の美観性",
      "振動・騒音・電流値・吐出圧力・漏水・軸受温度",
      "ポンプ室の壁面仕上げと床面の排水勾配"
    ],
    "a": 2
  },
  {
    "idx": 619,
    "genre": 4,
    "q": "揚水ポンプの「エア噛み」が発生する原因はどれか？",
    "o": [
      "吐出管の管径が必要以上に大きく設計されている",
      "吐出側の配管抵抗が設計値より大きくなっている",
      "ポンプ周辺の気温が低く水温が過度に低下している",
      "吸込管の空気漏入・水位低下・呼水不足が生じている"
    ],
    "a": 3
  },
  {
    "idx": 620,
    "genre": 4,
    "q": "揚水ポンプの「オーバーホール」の目安時期はどれか？",
    "o": [
      "毎月1回の定期点検時にあわせて実施する",
      "据付後20年を経過した時点で初回を実施する",
      "年1回の法定点検の際にあわせて実施する",
      "3～5年ごとに使用状況を踏まえて実施する"
    ],
    "a": 3
  },
  {
    "idx": 621,
    "genre": 4,
    "q": "揚水ポンプの「電流値の上昇」が示す異常はどれか？",
    "o": [
      "ポンプ内部の摩耗・インペラの異物噛み込み・軸受の劣化",
      "配管の保温材が経年劣化して断熱性能が低下した状態",
      "ポンプが設計通りの定格運転を維持している正常な状態",
      "吸込側の水温が低下して水の粘性が変化している状態"
    ],
    "a": 0
  },
  {
    "idx": 622,
    "genre": 4,
    "q": "ポンプの「チャーン運転（締切運転）」の目的はどれか？",
    "o": [
      "吐出弁を閉じた状態でポンプの締切圧力が規定値を満たすか確認する",
      "ポンプ内部に冷却水を循環させて軸受温度を下げる",
      "配管内に大量の水を流してフラッシング洗浄を行う",
      "水槽内の水を循環させて残留塩素の均一性を確認する"
    ],
    "a": 0
  },
  {
    "idx": 623,
    "genre": 4,
    "q": "ポンプの「キャビテーション」を防止する方法はどれか？",
    "o": [
      "NPSHaをNPSHr以上に確保し吸込管を短くして損失を低減する",
      "吐出管の管径を小さくして流速を上げ圧力損失を増加させる",
      "ポンプの設置場所を高くして揚程を大きくとる",
      "給水温度を意図的に上げて水の飽和蒸気圧に近づける"
    ],
    "a": 0
  },
  {
    "idx": 627,
    "genre": 4,
    "q": "ポンプの「電流値」が設計値より高い場合に疑うべき原因はどれか？",
    "o": [
      "吐出管の管径が設計値より大きく流量過多になっている",
      "吸込側の水温が低下し水の密度が変化している",
      "制御盤の表示灯が正常点灯しており運転に異常がない",
      "インペラの摩耗・異物噛込み・軸受劣化等の負荷増加"
    ],
    "a": 3
  },
  {
    "idx": 628,
    "genre": 4,
    "q": "「マグネットSSC（電磁接触器）」の点検で確認することはどれか？",
    "o": [
      "制御盤内の配線ルートと結束バンドの固定状態",
      "電磁接触器の設置高さと制御盤内の配置位置",
      "電磁接触器の製造メーカーと定格容量の記録照合",
      "接点の摩耗・焼損・動作音の異常・端子の緩み"
    ],
    "a": 3
  },
  {
    "idx": 629,
    "genre": 4,
    "q": "「ブレーカー」の点検で確認することはどれか？",
    "o": [
      "端子の緩み・変色・異臭・トリップテストの正常動作",
      "ブレーカーの設置高さと表面の塗装状態の確認",
      "ブレーカーの製造メーカーと定格遮断容量の記録照合",
      "ブレーカー周辺の配線ルートと結束バンドの固定状態"
    ],
    "a": 0
  },
  {
    "idx": 630,
    "genre": 4,
    "q": "「バルブチャッキ（逆止弁）」の点検で確認することはどれか？",
    "o": [
      "弁の外面塗装の劣化状態と再塗装の要否判定",
      "弁体の動作確認・異物付着・漏水・弁座の摩耗",
      "弁の製造メーカーと耐圧試験成績書の照合確認",
      "弁の設置方向と配管支持金物の取付状態の確認"
    ],
    "a": 1
  },
  {
    "idx": 631,
    "genre": 4,
    "q": "「カップリング」の摩耗を確認する目的はどれか？",
    "o": [
      "カップリングの外観を美しく保ち記録写真の品質を維持するため",
      "カップリングの材質変更が必要かどうかを判定するため",
      "カップリングの交換時期をメーカーに報告するため",
      "ポンプとモーターの接続部の劣化を発見し振動・異音・運転不良を防止するため"
    ],
    "a": 3
  },
  {
    "idx": 632,
    "genre": 4,
    "q": "「フート弁」の点検で確認することはどれか？",
    "o": [
      "弁の口径が設計図書の指定値と一致しているか",
      "弁の外面に施された防錆塗装の剥離状況",
      "弁体の開閉動作・異物付着・弁座の密閉性",
      "弁の製造銘板に記載された耐圧性能の確認"
    ],
    "a": 2
  },
  {
    "idx": 633,
    "genre": 4,
    "q": "「センサー類」の点検で確認する機器はどれか？",
    "o": [
      "空調設備の室内機と室外機の冷媒配管接続状態",
      "非常用照明器具のバッテリー残量と点灯時間の測定",
      "電極棒・フロートスイッチ・圧力センサー等の水位・圧力検知機器",
      "消火器の設置位置と使用期限の確認および外観検査"
    ],
    "a": 2
  },
  {
    "idx": 634,
    "genre": 4,
    "q": "「異常信号」の点検で確認することはどれか？",
    "o": [
      "制御盤の異常ランプが消灯していることと警報テストの正常動作",
      "警報ブザーの音量レベルが規定のデシベル値を満たしているか",
      "異常信号の発報履歴を制御盤のメーカーに報告する手順",
      "警報表示灯の発光色が法令で定められた色と一致しているか"
    ],
    "a": 0
  },
  {
    "idx": 635,
    "genre": 4,
    "q": "「ランプ類」の点検で確認することはどれか？",
    "o": [
      "表示灯のランプ交換費用と次回交換時期の見積り",
      "運転表示灯・異常表示灯・電源表示灯等の点灯・消灯が正常か",
      "表示灯の発光色が設備の塗装色と調和しているか",
      "表示灯の製造メーカーと消費電力の仕様照合"
    ],
    "a": 1
  },
  {
    "idx": 636,
    "genre": 4,
    "q": "「配線端子」の点検で確認することはどれか？",
    "o": [
      "端子の緩み・変色（過熱痕）・被覆の損傷",
      "端子の発光色とケーブル被覆の色の対応関係",
      "端子の購入単価と在庫数量の管理台帳との照合",
      "端子の製造メーカーと定格電流値の仕様確認"
    ],
    "a": 0
  },
  {
    "idx": 637,
    "genre": 4,
    "q": "「水槽の本体・架台」の点検で確認することはどれか？",
    "o": [
      "水槽の製造メーカーと保証期間の残存日数の確認",
      "亀裂・変形・腐食・漏水・架台のずれやボルトの緩み",
      "水槽の外面塗装色が建物の景観基準に適合しているか",
      "水槽の容量が現在の使用水量に対して過大でないか"
    ],
    "a": 1
  },
  {
    "idx": 638,
    "genre": 4,
    "q": "「配管状態」の点検で確認することはどれか？",
    "o": [
      "腐食・漏水・保温材の損傷・支持金物のずれ",
      "配管の製造メーカーと材質証明書の記載内容",
      "配管の外面塗装色が用途別の識別色と一致しているか",
      "配管の口径が設計図書の指定値と合致しているか"
    ],
    "a": 0
  },
  {
    "idx": 639,
    "genre": 4,
    "q": "「汚濁状態」の点検で確認することはどれか？",
    "o": [
      "水槽の材質がFRPかステンレスかを再確認する",
      "水槽の有効容量が設計図書と一致しているか計測する",
      "水槽の外面に付着した汚れの清掃時期を判断する",
      "水槽内の水の色・濁り・異物・藻の繁殖・沈殿物の有無"
    ],
    "a": 3
  },
  {
    "idx": 640,
    "genre": 4,
    "q": "「入排水異常」の点検で確認することはどれか？",
    "o": [
      "給水と排水の状態が正常か・音の異常・流量の異常を確認する",
      "配管の口径が設計値に適合しているかノギスで計測する",
      "配管外面の塗装色が用途別の識別基準と一致しているか",
      "配管の全長を測定して設計図書の寸法と照合する"
    ],
    "a": 0
  },
  {
    "idx": 641,
    "genre": 4,
    "q": "「施錠」の点検で確認することはどれか？",
    "o": [
      "鍵の保管場所が管理室の施錠可能な棚に限定されているか",
      "鍵の製造メーカーとシリンダー型番の照合記録を確認する",
      "鍵の予備数量と最終複製日の管理台帳との整合を確認する",
      "マンホール蓋・ポンプ室・水槽周辺の施錠が確実にされているか"
    ],
    "a": 3
  },
  {
    "idx": 642,
    "genre": 4,
    "q": "「逆流防止器」の点検で確認する項目はどれか？",
    "o": [
      "逆流防止器の設置年月日と保証期間の残存日数のみ",
      "第一逆止弁・第二逆止弁・閉止弁・逃し弁の作動テストと排水確認",
      "逆流防止器の外観と塗装の劣化状態のみを目視確認",
      "逆流防止器のメーカー名と型式の銘板記載事項のみ"
    ],
    "a": 1
  },
  {
    "idx": 643,
    "genre": 4,
    "q": "逆流防止器の「逃し弁作動テスト」の目的はどれか？",
    "o": [
      "逃し弁の取付方向が上流・下流で正しいか確認する",
      "逃し弁の設定圧力を変更して流量を増加させる",
      "逆流が発生した際に逃し弁が正常に開いて排水するか確認する",
      "逃し弁の口径が設計図書の指定値と一致しているか計測する"
    ],
    "a": 2
  },
  {
    "idx": 645,
    "genre": 4,
    "q": "「圧力タンク」の「封入圧」の点検で確認することはどれか？",
    "o": [
      "タンク内の空気圧が設計値を維持しているか確認する",
      "タンクの外面塗装が劣化して錆が発生していないか",
      "タンクの総重量が架台の許容荷重を超えていないか",
      "タンクの製造メーカーと耐圧試験成績書の照合"
    ],
    "a": 0
  },
  {
    "idx": 646,
    "genre": 4,
    "q": "「給水ユニット」の「製造No」を記録する目的はどれか？",
    "o": [
      "年次の保守点検コストを算定する際の基礎資料とする",
      "設備更新時に既存ユニットの仕様を変更するための参考にする",
      "機器の特定・メーカー問合せ・部品手配・履歴管理に使用する",
      "建物の固定資産台帳に記載して減価償却費を算定する"
    ],
    "a": 2
  },
  {
    "idx": 647,
    "genre": 4,
    "q": "ポンプの「全揚程」とは何か？",
    "o": [
      "ポンプが水を押し上げられる最大の高さで配管損失を含む",
      "ポンプ本体の基礎面から吐出口までの垂直高さ",
      "ポンプの外殻ケーシングの内径と外径の差の寸法",
      "ポンプの据付位置から受水槽の底面までの落差"
    ],
    "a": 0
  },
  {
    "idx": 648,
    "genre": 4,
    "q": "ポンプの「給水量」の単位はどれか？",
    "o": [
      "℃（摂氏温度）",
      "L/min（リットル毎分）",
      "MPa（メガパスカル）",
      "MΩ（メガオーム）"
    ],
    "a": 1
  },
  {
    "idx": 649,
    "genre": 4,
    "q": "点検時に「手動運転」を行う目的はどれか？",
    "o": [
      "ポンプを手動で起動・停止して正常に動作するか確認する",
      "水槽内の残留塩素濃度を計測して水質基準との適合を検査する",
      "配管内のスケールや異物を除去するためフラッシング洗浄を行う",
      "自動制御盤のプログラムを書き換えて設定値を更新する"
    ],
    "a": 0
  },
  {
    "idx": 650,
    "genre": 4,
    "q": "点検時に「運転状態」を確認する項目はどれか？",
    "o": [
      "振動・騒音・発熱・漏水が正常範囲内か",
      "ポンプの外面塗装の状態と再塗装の要否判定",
      "ポンプの製造年月と設計耐用年数の残存期間",
      "ポンプ室の照明器具と換気設備の動作確認"
    ],
    "a": 0
  },
  {
    "idx": 651,
    "genre": 4,
    "q": "「圧力スイッチ」の起動圧力と停止圧力の関係はどれか？",
    "o": [
      "起動圧力と停止圧力は常に同じ値に設定する",
      "起動圧力と停止圧力の設定は制御に影響しない",
      "起動圧力＜停止圧力で圧力低下で起動し上昇で停止する",
      "起動圧力＞停止圧力で圧力上昇で起動し低下で停止する"
    ],
    "a": 2
  },
  {
    "idx": 652,
    "genre": 4,
    "q": "点検で「防虫網」の確認が重要な理由はどれか？",
    "o": [
      "破損すると虫やネズミが水槽内に侵入し水質汚染の原因になるため",
      "防虫網が詰まるとポンプの吐出圧力が低下して給水不良になるため",
      "防虫網の材質が劣化すると通気管の排気音が大きくなるため",
      "防虫網が脱落するとマンホール蓋の施錠ができなくなるため"
    ],
    "a": 0
  },
  {
    "idx": 653,
    "genre": 4,
    "q": "点検で「各バルブ」を確認する目的はどれか？",
    "o": [
      "バルブの外面塗装色が配管の用途識別基準と一致しているか確認する",
      "開閉が正常に行えるか・漏水がないか・固着していないか確認する",
      "バルブの購入単価を確認して次回予算の見積りに反映させる",
      "バルブの製造メーカーと定格圧力の銘板表示を記録する"
    ],
    "a": 1
  },
  {
    "idx": 654,
    "genre": 4,
    "q": "点検報告書の「特記事項」に記載すべき内容はどれか？",
    "o": [
      "通常の点検項目では記載しきれない異常・改善提案・経過観察事項",
      "点検作業員の保有資格一覧と受講した安全教育の履歴",
      "点検当日の天気・気温・湿度などの気象条件の詳細記録",
      "建物の竣工年月日と過去の大規模修繕工事の実施履歴"
    ],
    "a": 0
  },
  {
    "idx": 655,
    "genre": 4,
    "q": "「巡回設備点検」で建物の外観を確認する目的はどれか？",
    "o": [
      "建物の外面塗装色が管理規約の基準に適合しているか確認する",
      "建物の竣工年月日を銘板で確認して築年数を算出する",
      "外壁の亀裂・漏水痕・設備の異常・安全上の問題を早期発見する",
      "建物の延床面積が登記簿の記載と一致しているか確認する"
    ],
    "a": 2
  },
  {
    "idx": 656,
    "genre": 4,
    "q": "点検で「絶縁抵抗」が低下している場合に疑うべき原因はどれか？",
    "o": [
      "給水温度が季節変動により設計条件から外れている",
      "ポンプが設計通りの定格出力で正常運転を継続している",
      "配線の劣化・水分の侵入・絶縁体の破損が発生している",
      "配管外面の識別塗装色が経年により退色している"
    ],
    "a": 2
  },
  {
    "idx": 658,
    "genre": 4,
    "q": "点検時の「電流値測定」に使用する測定器はどれか？",
    "o": [
      "ブルドン管式の圧力計",
      "メガー（絶縁抵抗計）",
      "気泡管式の水平器",
      "クランプメーター（クランプ式電流計）"
    ],
    "a": 3
  },
  {
    "idx": 659,
    "genre": 4,
    "q": "「排水ポンプ」の種類のうち「湧水ポンプ」の用途はどれか？",
    "o": [
      "厨房から発生するグリスを含んだ排水を汲み上げる",
      "屋上に溜まった雨水を排水管を通じて地上に排出する",
      "地下に湧き出す地下水を汲み上げて排出する",
      "トイレのし尿を含む汚水を地上の下水管まで排出する"
    ],
    "a": 2
  },
  {
    "idx": 660,
    "genre": 4,
    "q": "「排水ポンプ」の種類のうち「汚水ポンプ」の用途はどれか？",
    "o": [
      "トイレ等のし尿を含む汚水を排出する",
      "空調機のドレン水を排出するために使用する",
      "屋上や敷地内に溜まった雨水を排出する",
      "地下に湧き出す地下水を汲み上げて排出する"
    ],
    "a": 0
  },
  {
    "idx": 661,
    "genre": 4,
    "q": "「排水ポンプ」の種類のうち「雑排水ポンプ」の用途はどれか？",
    "o": [
      "トイレのし尿を含む汚水を地上の下水管まで圧送する",
      "厨房・浴室・洗面等のし尿を含まない排水を排出する",
      "消火設備の試験排水を一時貯留槽から屋外に排出する",
      "地下に湧き出す地下水を汲み上げて排水管に送る"
    ],
    "a": 1
  },
  {
    "idx": 662,
    "genre": 4,
    "q": "点検報告書の「写真撮影」で必要な場面はどれか？",
    "o": [
      "点検当日の天候状況を記録するための空の撮影",
      "建物外観・設備全景・異常箇所・計器の読み値・作業前後の撮影",
      "点検作業員の顔写真と保有資格証のみの撮影",
      "建物周辺の街並みや近隣建物との位置関係の撮影"
    ],
    "a": 1
  },
  {
    "idx": 663,
    "genre": 4,
    "q": "点検で「マンホール」の確認項目はどれか？",
    "o": [
      "マンホールの外面塗装色と設置年月日の銘板表示",
      "マンホールの製造メーカーと耐荷重性能の仕様照合",
      "マンホールの開口寸法と水槽内部への作業員の出入り可否",
      "防水パッキンの状態・施錠の有無・蓋の破損や変形"
    ],
    "a": 3
  },
  {
    "idx": 664,
    "genre": 4,
    "q": "設備点検の「頻度」として一般的な建物巡回点検の周期はどれか？",
    "o": [
      "5年に1回の大規模修繕時にあわせて実施する",
      "毎日の日常巡回として設備管理者が全項目を確認する",
      "10年に1回の法定点検時にのみ実施する",
      "月1回～年数回を建物の規模や用途に応じて設定する"
    ],
    "a": 3
  },
  {
    "idx": 665,
    "genre": 4,
    "q": "点検報告書の「指摘箇所」に△（経過観察）と記載する基準はどれか？",
    "o": [
      "点検項目に全く問題がなく良好な状態を維持している場合",
      "現時点では使用に支障ないが今後悪化の可能性があり継続監視が必要な場合",
      "設備の機能に支障があり直ちに修理や交換が必要な場合",
      "該当する設備が撤去済みで点検対象から外れている場合"
    ],
    "a": 1
  },
  {
    "idx": 666,
    "genre": 4,
    "q": "点検報告書の「指摘箇所」に×（要改善）と記載する基準はどれか？",
    "o": [
      "現時点で問題はないが今後悪化の可能性があり経過観察が必要な場合",
      "設備の機能に支障があり修理・交換等の改善が必要な場合",
      "該当する設備が撤去済みで点検の対象外となっている場合",
      "点検項目に全く問題がなく設備が正常に機能している場合"
    ],
    "a": 1
  },
  {
    "idx": 667,
    "genre": 4,
    "q": "「二重式逆流防止器」の点検で記載する項目はどれか？",
    "o": [
      "閉止弁・逃し弁を含む全ての弁の作動テストを記録する",
      "閉止弁の開閉動作と外観のみを確認して記録する",
      "逃し弁の作動テストと排水確認のみを実施して記録する",
      "第一逆止弁と第二逆止弁の動作確認のみを記録する"
    ],
    "a": 3
  },
  {
    "idx": 668,
    "genre": 4,
    "q": "「排水ポンプ」の点検で「フロートスイッチ」を確認する理由はどれか？",
    "o": [
      "フロートスイッチの動作音がポンプ室の騒音基準を超えていないか確認するため",
      "フロートスイッチの外観が汚損して点検記録の写真撮影に支障がないか確認するため",
      "フロートスイッチの設置位置が排水槽の有効容量に影響していないか確認するため",
      "水位検知が正常でないとポンプの起動停止が不能になり溢水や空転の原因になるため"
    ],
    "a": 3
  },
  {
    "idx": 1210,
    "genre": 4,
    "q": "エレベーターの法定点検の実施頻度はどれか",
    "o": [
      "毎週1回の定期巡回点検として実施する",
      "1年に1回以上の頻度で実施する",
      "毎月1回の保守点検として実施する",
      "毎日の始業前点検として実施する"
    ],
    "a": 1
  },
  {
    "idx": 1216,
    "genre": 4,
    "q": "排煙設備の排煙口の設置基準で正しいものはどれか",
    "o": [
      "床面から30cm以内の壁面に設置する",
      "天井面又は壁の上部で天井面から80cm以内に設置する",
      "壁の中間の高さに設置する",
      "床面から1mの高さの壁面に設置する"
    ],
    "a": 1
  },
  {
    "idx": 1217,
    "genre": 4,
    "q": "給水ポンプのキャビテーションが発生する条件はどれか",
    "o": [
      "吸込み側の圧力が低下し液体が局所的に沸騰する",
      "吐出し側の流量が設計値より少なくなっている",
      "吐出し側の圧力が設計値より高くなっている",
      "吸込み側の水温が設計値より低くなっている"
    ],
    "a": 0
  },
  {
    "idx": 1218,
    "genre": 4,
    "q": "受変電設備の「漏電火災警報器」の設置が義務付けられる建物はどれか",
    "o": [
      "延床面積に関わらず全ての建物に設置が義務付けられる",
      "工場や倉庫等の産業施設のみに設置が義務付けられる",
      "戸建住宅を含む全ての住宅に設置が義務付けられる",
      "特定防火対象物で契約電流容量が一定以上のものに設置が義務付けられる"
    ],
    "a": 3
  },
  {
    "idx": 1219,
    "genre": 4,
    "q": "ボイラーの点検で「水位計」の確認事項はどれか",
    "o": [
      "ボイラー水のpH値と硬度を測定して水質基準との適合を確認する",
      "ボイラー本体の外面塗装に錆や腐食が発生していないか確認する",
      "煙突の排気温度と排ガス濃度を測定して燃焼状態を確認する",
      "水位計のガラス管の汚れ・損傷と正常な水位表示を確認する"
    ],
    "a": 3
  },
  {
    "idx": 1221,
    "genre": 4,
    "q": "非常放送設備の起動方法として正しいものはどれか",
    "o": [
      "タイマーにより設定した時刻に自動で起動する",
      "照明スイッチと連動して消灯時に自動起動する",
      "防災センターの手動スイッチのみで起動する",
      "自動火災報知設備と連動して自動起動する"
    ],
    "a": 3
  },
  {
    "idx": 1223,
    "genre": 4,
    "q": "給水設備の「減圧弁」の設置目的はどれか",
    "o": [
      "配管の方向を変えるために管路の途中に設置する",
      "給水管内の流量を増加させるために設置する",
      "給水の水質を浄化するためにフィルターとして設置する",
      "上流側の高い圧力を下流側で一定の低い圧力に調整するために設置する"
    ],
    "a": 3
  },
  {
    "idx": 1224,
    "genre": 4,
    "q": "排水ポンプの「フロートスイッチ」の役割はどれか",
    "o": [
      "排水の温度変化を検知してポンプの出力を制御する",
      "排水の水質を測定して基準値を超えた場合に警報を発する",
      "排水管内の圧力変動を測定して逆流を防止する",
      "水位の変動に応じてポンプの自動発停を行う"
    ],
    "a": 3
  },
  {
    "idx": 1226,
    "genre": 4,
    "q": "建築設備の「中間検査」が行われるタイミングはどれか",
    "o": [
      "工事の中間段階で配管の隠蔽前等に実施する",
      "建物の入居者が使用を開始した後に実施する",
      "建物の竣工検査が完了した後に追加で実施する",
      "設計図書の承認が完了した段階で実施する"
    ],
    "a": 0
  },
  {
    "idx": 1227,
    "genre": 4,
    "q": "ガス漏れ警報器の設置位置として正しいものはどれか（都市ガス13Aの場合）",
    "o": [
      "天井面から30cm以内の位置に設置する",
      "ガスメーター付近の屋外壁面に設置する",
      "床面から30cm以内の位置に設置する",
      "壁の中間の高さ（床面から約1m）に設置する"
    ],
    "a": 0
  },
  {
    "idx": 1296,
    "genre": 4,
    "q": "スプリンクラーヘッドの標準型の作動温度区分で、使用場所が一般の場合の表示色はどれか？",
    "o": [
      "青色（高温部用72～96℃未満）",
      "白色（無色）（一般用68℃または72℃）",
      "赤色（極高温部用121～162℃未満）",
      "黄色（高温部用96～121℃未満）"
    ],
    "a": 1
  },
  {
    "idx": 1320,
    "genre": 4,
    "q": "配管のウォーターハンマー（水撃）防止対策として、最も効果的なものはどれか？",
    "o": [
      "配管の勾配を大きくして排水の流速を上げる",
      "バルブの開閉速度を速くして操作時間を短縮する",
      "配管径を小さくして管内の流速を制限する",
      "エアチャンバーまたはショックアブソーバーを設置する"
    ],
    "a": 3
  },
  {
    "idx": 1325,
    "genre": 4,
    "q": "真空式温水発生機と無圧式温水発生機の違いとして正しいものはどれか？",
    "o": [
      "無圧式は大気圧で運転するためボイラーに該当する",
      "真空式は缶体内を大気圧以上で運転するため定期検査が必要",
      "真空式は缶体内を真空で運転しボイラーに該当しない",
      "真空式は高圧で運転するため無圧式より危険性が高い"
    ],
    "a": 2
  },
  {
    "idx": 1434,
    "genre": 4,
    "q": "非常用発電機の負荷試験で確認する項目として最も重要なものはどれか？",
    "o": [
      "発電機の外装パネルの塗装状態と腐食の有無",
      "定格出力の30%以上の負荷で正常運転できること",
      "発電機の運転中の騒音レベルが規制値以下であること",
      "発電機の設置場所の室温が規定範囲内であること"
    ],
    "a": 1
  },
  {
    "idx": 2344,
    "genre": 4,
    "q": "JIS（日本産業規格）の配管用図示記号において、仕切弁を表す記号の形状はどれか",
    "o": [
      "二等辺三角形を2つ合わせた蝶ネクタイ形",
      "丸の中に十字を描いたバタフライ弁の記号",
      "四角の中にX字を描いた玉形弁の記号",
      "丸の中に矢印を描いた逆止弁の記号"
    ],
    "a": 0
  },
  {
    "idx": 2371,
    "genre": 4,
    "q": "エレベーターの安全装置で、ロープが切れた場合に作動するものはどれか",
    "o": [
      "調速機（ガバナー）と非常止め装置が連動して作動する",
      "リミットスイッチが最上階で作動して巻上機を停止させる",
      "ドアインターロックが作動して扉の開閉を制御する",
      "着床装置が作動して最寄り階に停止させる"
    ],
    "a": 0
  },
  {
    "idx": 2387,
    "genre": 4,
    "q": "建築物の換気設備において、必要換気量の算定基準として最も一般的に使用されるものはどれか",
    "o": [
      "室内の相対湿度の上限値を基準とする",
      "室内のCO2濃度を基準として算定する",
      "室内の乾球温度の上限値を基準とする",
      "室内の照度レベルの維持基準とする"
    ],
    "a": 1
  },
  {
    "idx": 2389,
    "genre": 4,
    "q": "建築物の給排水設備で、通気管の主な目的として正しいものはどれか",
    "o": [
      "給水管内の圧力を増加させて上階への給水能力を高める",
      "排水管内の空気圧変動を緩和しトラップの封水を保護する",
      "汚水を屋外の浄化槽へ自然流下で排出するための勾配を確保する",
      "屋上に降った雨水を一時的に貯留して流出量を調整する"
    ],
    "a": 1
  },
  {
    "idx": 2534,
    "genre": 4,
    "q": "電気温水器の沸き上げ運転中に、貯湯ユニット下部の排水配管から水が滴り落ちる現象の原因として正しいものはどれか",
    "o": [
      "給水管の接続部から配管の破損による漏水が発生している",
      "水が加熱されて膨張した分が逃し弁から排出される正常な現象",
      "循環ポンプの故障により温水が逆流して溢れ出ている",
      "貯湯タンクの内面に腐食が進行して穴が開いている"
    ],
    "a": 1
  },
  {
    "idx": 2536,
    "genre": 4,
    "q": "電気温水器の「逃し弁（安全弁）」の役割として正しいものはどれか",
    "o": [
      "貯湯タンク内の水温を設定値に自動調節する役割を持つ",
      "タンク内の圧力が一定以上になったとき膨張水を排出してタンクを保護する",
      "貯湯タンク内の温水を配管全体に循環させる役割を持つ",
      "貯湯タンクに流入する水の不純物を除去して浄化する"
    ],
    "a": 1
  },
  {
    "idx": 2540,
    "genre": 4,
    "q": "受水槽の水位制御盤で「減水」警報が発報した場合、最初に確認すべきことはどれか",
    "o": [
      "受水槽の外面塗装の剥離やFRPパネルの変色がないか確認する",
      "受水槽への給水が正常に行われているか定水位弁やボールタップの動作を確認する",
      "排水管の清掃状態と排水口の詰まりがないか確認する",
      "電気温水器の沸き上げ温度と貯湯量が正常か確認する"
    ],
    "a": 1
  },
  {
    "idx": 2542,
    "genre": 4,
    "q": "受水槽の水位制御盤で「湯水停止」の設定値（例：50）が「減水」の設定値（例：100）より低い理由はどれか",
    "o": [
      "制御盤の設定ミスであり本来は同じ値に設定すべきである",
      "減水警報後もなお水位が下がり続ける場合にポンプの空運転を防止するため強制停止する",
      "湯水停止は減水より重要度が低いため小さい値に設定されている",
      "設定値の数値自体には制御上の意味はなく管理用の識別番号である"
    ],
    "a": 1
  },
  {
    "idx": 2550,
    "genre": 4,
    "q": "給水ポンプの点検で「絶縁抵抗値」を測定する目的はどれか",
    "o": [
      "ポンプの吐出流量が設計値を維持しているか確認するため",
      "給水の残留塩素濃度が水質基準に適合しているか確認するため",
      "配管内の水圧が各階の給水に必要な圧力を維持しているか確認するため",
      "電動機の絶縁劣化を検出して漏電や感電事故を防止するため"
    ],
    "a": 3
  },
  {
    "idx": 2551,
    "genre": 4,
    "q": "給排水設備の点検で「フート弁」の点検が必要な理由はどれか",
    "o": [
      "フート弁は吸込管の水温を一定に制御する機能を持つため",
      "フート弁は吐出側の水圧を増加させる機能を持つため",
      "フート弁は排水管のトラップとして臭気を遮断する機能を持つため",
      "フート弁が故障すると吸込管の水が落下してポンプが空転する原因になるため"
    ],
    "a": 3
  },
  {
    "idx": 2552,
    "genre": 4,
    "q": "給排水設備の点検報告書で、水槽廻りの点検項目に含まれるものはどれか",
    "o": [
      "本体・架台の状態、配管状態、汚濁状態、電極設備、マンホール、防虫網・通気管、各バルブ、施錠",
      "ポンプの電流値の測定結果のみを記録する",
      "排水管の高圧洗浄の清掃状態のみを確認する",
      "エレベーターの安全装置の作動試験を実施する"
    ],
    "a": 0
  },
  {
    "idx": 2553,
    "genre": 4,
    "q": "給排水設備の点検で「逆流防止器（二重式逆流防止器）」の点検項目に含まれるものはどれか",
    "o": [
      "第一逆止弁と第二逆止弁の動作確認、逃し弁の作動テスト、逃し弁の排水確認",
      "建物外壁の塗装剥離と防水層の劣化状態の確認",
      "ガス配管の気密試験による漏れの有無の検査",
      "非常用照明器具のバッテリー残量と点灯時間の測定"
    ],
    "a": 0
  },
  {
    "idx": 2554,
    "genre": 4,
    "q": "給排水設備の点検で「制御関連機器」として確認すべき項目に含まれるものはどれか",
    "o": [
      "ブレーカー、マグネット/SSC、異常信号、ランプ類、センサー類、配線端子、外観",
      "配管の口径測定と設計図書との照合のみを実施する",
      "水質検査として残留塩素とpH値の測定のみを実施する",
      "屋上の防水層の劣化状態と雨水排水溝の清掃状態の確認"
    ],
    "a": 0
  },
  {
    "idx": 2556,
    "genre": 4,
    "q": "給排水設備の点検で、ポンプの「グランドパッキン」と「メカニカルシール」はどちらもポンプのどの部分の部品か",
    "o": [
      "羽根車（インペラー）を構成する回転翼の部品",
      "吐出口のフランジ接続部を密閉する部品",
      "軸封部で回転軸と本体の隙間をシールする部品",
      "吸込口のストレーナーを固定する部品"
    ],
    "a": 2
  },
  {
    "idx": 2557,
    "genre": 4,
    "q": "給排水設備の点検で、ポンプの「カップリング」の摩耗を確認する理由はどれか",
    "o": [
      "カップリングの外観が汚損すると点検報告書の写真記録に支障があるため",
      "カップリングの表面色が変化すると材質の特定が困難になるため",
      "カップリングが摩耗すると電動機の動力がポンプに正しく伝わらず異常振動や騒音の原因になるため",
      "カップリングの表面温度を測定してポンプの運転時間を推定するため"
    ],
    "a": 2
  },
  {
    "idx": 2559,
    "genre": 4,
    "q": "受水槽の電極式水位制御で「共通極（アース極）」が常に水に浸かっていなければならない理由はどれか",
    "o": [
      "共通極が水温の変化を感知して制御盤に信号を送るため",
      "共通極を通じて水槽内の水流を制御して水を循環させるため",
      "他の電極との間で通電して水位を検知するための基準極だから",
      "共通極の表面に防食電流を流して電極の腐食を防ぐため"
    ],
    "a": 2
  },
  {
    "idx": 2578,
    "genre": 4,
    "q": "自動空気抜き弁の内部構造で、空気を排出する仕組みとして正しいものはどれか",
    "o": [
      "電動モーターの回転力でバルブの弁体を開閉する",
      "タイマー制御により一定間隔でソレノイドバルブを開閉する",
      "フロートが水位に応じて上下し空気孔を自動的に開閉する",
      "圧力スイッチの信号で電磁弁を開閉して空気を排出する"
    ],
    "a": 2
  },
  {
    "idx": 2580,
    "genre": 4,
    "q": "寒冷地の屋外配管に空気抜き弁を設置する場合、凍結防止のために講じるべき対策として正しいものはどれか",
    "o": [
      "空気抜き弁の設置を省略して手動で空気を抜く運用にする",
      "空気抜き弁を凍結深度以下の地中に直接埋設する",
      "保温材で被覆し必要に応じてヒーター（凍結防止帯）を巻く",
      "冬季は空気抜き弁を取り外して春に再設置する"
    ],
    "a": 2
  },
  {
    "idx": 899,
    "genre": 5,
    "q": "KY活動（危険予知活動）の基本4ラウンド法で最初に行うステップはどれか",
    "o": [
      "抽出した危険のポイントを重要度順に絞り込む",
      "絞り込んだ危険に対して具体的な行動目標を設定する",
      "目標達成のための具体的な対策を立てる",
      "作業の状況を観察してどんな危険が潜んでいるか現状を把握する"
    ],
    "a": 3
  },
  {
    "idx": 902,
    "genre": 5,
    "q": "電話応対で相手の名前を聞き取れなかった場合の正しい対応はどれか",
    "o": [
      "聞き取れなかった点は保留にして用件だけを先に確認する",
      "「え？何ですか？」と率直に聞き返して確認する",
      "聞こえた部分から推測して対応を進める",
      "「恐れ入りますが、もう一度お名前をお伺いできますか」と丁寧に聞き返す"
    ],
    "a": 3
  },
  {
    "idx": 904,
    "genre": 5,
    "q": "ツールボックスミーティング（TBM）の主な目的はどれか",
    "o": [
      "当日の昼食休憩の時間帯と場所を作業班ごとに決める",
      "工事費用の変更点や追加見積りの内容を関係者間で打ち合わせる",
      "使用する工具の在庫数量を確認して不足分を発注する",
      "作業開始前に当日の作業内容と危険ポイントを共有する"
    ],
    "a": 3
  },
  {
    "idx": 910,
    "genre": 5,
    "q": "現場で外国人労働者とコミュニケーションを取る際に最も重要なことはどれか",
    "o": [
      "通訳がいない場合は安全上の理由から作業を中止させる",
      "日本語を十分に話せない場合は作業班から外して別の業務を割り当てる",
      "やさしい日本語・図・ジェスチャーを活用して安全情報を確実に伝える",
      "英語のみで指示を出して理解度は本人の自己責任とする"
    ],
    "a": 2
  },
  {
    "idx": 913,
    "genre": 5,
    "q": "近隣住民への工事前挨拶で伝えるべき内容として最も重要なものはどれか",
    "o": [
      "設計図面の詳細な仕様と構造計算の概要を説明する",
      "使用する材料の品名・数量・搬入スケジュールの一覧を渡す",
      "工事期間・作業時間・騒音の可能性と緊急時の連絡先を伝える",
      "工事費用の総額と発注者との契約条件の概要を説明する"
    ],
    "a": 2
  },
  {
    "idx": 915,
    "genre": 5,
    "q": "現場の指差し呼称の正しい手順はどれか",
    "o": [
      "目を閉じて集中した状態で対象の安全を心の中で確認する",
      "対象を指差し、声に出して確認し、指を振り下ろす",
      "他の作業員に確認を任せて自分は次の作業に移る",
      "声を出さずに指だけ対象に向けて安全を目視確認する"
    ],
    "a": 1
  },
  {
    "idx": 916,
    "genre": 5,
    "q": "施主との打ち合わせで意見が対立した場合の最も適切な対応はどれか",
    "o": [
      "打ち合わせをいったん中止して後日仕切り直す",
      "その場で技術的な正当性を強く主張して施主を説得する",
      "施主の要望は現場の判断で対応が難しいため全て断る",
      "施主の意見を傾聴し技術的根拠に基づいて代替案を提案する"
    ],
    "a": 3
  },
  {
    "idx": 924,
    "genre": 5,
    "q": "見積書に記載すべき必須項目として最も重要なものはどれか",
    "o": [
      "過去に施工した類似工事の完成写真と施主の評価コメント",
      "施工を担当する作業員の保有資格一覧と顔写真",
      "工事名称・工事内容・金額・有効期限を明記する",
      "会社の沿革と経営理念および代表者の挨拶文"
    ],
    "a": 2
  },
  {
    "idx": 926,
    "genre": 5,
    "q": "現場で事故が発生した場合の最優先事項はどれか",
    "o": [
      "事故原因の調査と責任者の特定を最優先で行う",
      "証拠保全のために現場状況を写真撮影する",
      "被災者の救護と二次災害の防止を最優先で行う",
      "事故報告書を作成して監督官庁に速やかに届け出る"
    ],
    "a": 2
  },
  {
    "idx": 927,
    "genre": 5,
    "q": "セクシュアルハラスメントに該当する行為はどれか",
    "o": [
      "作業効率を考慮して男女混合の班編成を行う",
      "業務上必要な救護や介助のために身体に接触する",
      "安全上の理由から男女を問わず共同作業を指示する",
      "相手が不快と感じる性的な言動を繰り返す"
    ],
    "a": 3
  },
  {
    "idx": 929,
    "genre": 5,
    "q": "現場の整理整頓で「整理」の正しい意味はどれか",
    "o": [
      "定められたルールや手順を現場全員が守ること",
      "物品をきれいに並べて見た目を整えること",
      "必要なものと不要なものを分け不要なものを処分すること",
      "作業場所や通路の清掃を毎日欠かさず行うこと"
    ],
    "a": 2
  },
  {
    "idx": 931,
    "genre": 5,
    "q": "現場のゲート管理で入場時に確認すべき最も重要な項目はどれか",
    "o": [
      "作業員の通勤経路と最寄り駅からの所要時間の確認",
      "安全教育の受講確認と保険加入状況の確認",
      "作業員の過去の勤務先と在籍期間の確認",
      "作業員の健康診断の受診医療機関と検査内容の確認"
    ],
    "a": 1
  },
  {
    "idx": 933,
    "genre": 5,
    "q": "工事現場で許可なく撮影した写真をSNSに投稿する行為の問題点はどれか",
    "o": [
      "撮影の技術的な品質が低いため問題になることがある",
      "プライベートのSNSであっても閲覧制限があれば問題ない",
      "守秘義務違反・個人情報漏洩・セキュリティリスクがある",
      "撮影自体は自由であり投稿先を選べば問題はない"
    ],
    "a": 2
  },
  {
    "idx": 936,
    "genre": 5,
    "q": "作業許可書（Permit to Work）制度が適用される作業はどれか",
    "o": [
      "事務所内での書類整理や資料作成等の日常軽作業に適用される",
      "高所・密閉空間・火気使用等の高危険作業に適用される",
      "作業区域の清掃や廃材の片付け等の整理作業に適用される",
      "事務所での打ち合わせや会議への参加等に適用される"
    ],
    "a": 1
  },
  {
    "idx": 941,
    "genre": 5,
    "q": "工事完了報告書に記載すべき項目として最も重要なものはどれか",
    "o": [
      "工事概要・完了日・施工写真・検査結果を記載する",
      "作業員全員の趣味や特技を一覧にして記載する",
      "工事期間中の毎日の天気予報と実際の気象データを記載する",
      "現場周辺の飲食店情報と休憩場所の利用状況を記載する"
    ],
    "a": 0
  },
  {
    "idx": 944,
    "genre": 5,
    "q": "作業指示を出す際の「6W2H」の「2H」に含まれるものはどれか",
    "o": [
      "Hard（難易度）とHeavy（重量）を指す",
      "High（高さ）とHot（温度）を指す",
      "How to（方法）とHow much（費用・数量）を指す",
      "Happy（満足度）とHelpful（有用性）を指す"
    ],
    "a": 2
  },
  {
    "idx": 945,
    "genre": 5,
    "q": "ゼロ災運動が目指すものはどれか",
    "o": [
      "職場のあらゆる労働災害をゼロにすることを目指す",
      "工事にかかるコストをゼロに近づけることを目指す",
      "工事の利益率をゼロにして原価で受注することを目指す",
      "作業員の残業時間をゼロにして労働環境を改善する"
    ],
    "a": 0
  },
  {
    "idx": 946,
    "genre": 5,
    "q": "電話を受けた際、相手が名乗らなかった場合の対応はどれか",
    "o": [
      "名乗らない相手とは話をせずすぐに電話を切る",
      "「恐れ入りますが、お名前をお伺いできますか」と丁寧に確認する",
      "相手の名前は聞かずに用件だけを確認して対応を進める",
      "相手が名乗るまで無言のまま待ち続ける"
    ],
    "a": 1
  },
  {
    "idx": 947,
    "genre": 5,
    "q": "安全大会の主な目的はどれか",
    "o": [
      "安全意識の向上と全員の安全目標の共有を図る",
      "自社の新製品や新サービスを関係者に紹介して宣伝する",
      "工事関係者の親睦を深めるための懇親会を開催する",
      "前年度の売上実績と今期の利益目標を報告する"
    ],
    "a": 0
  },
  {
    "idx": 949,
    "genre": 5,
    "q": "現場で「ご安全に！」と声を掛け合う目的はどれか",
    "o": [
      "安全意識の相互確認と安全文化の醸成を図る",
      "作業の効率化には関係がないため時間の無駄である",
      "特に意味のない形式的な挨拶にすぎない",
      "上司や元請けの担当者へ真面目さをアピールする"
    ],
    "a": 0
  },
  {
    "idx": 952,
    "genre": 5,
    "q": "現場の朝礼で体調不良を申し出た作業員への対応として最も適切なものはどれか",
    "o": [
      "朝礼の場で全員の前で体調管理の不備を指摘する",
      "症状を確認し必要に応じて休養や医療機関の受診を指示する",
      "自己申告は過信できないため体調不良の訴えは受け付けない",
      "気合と根性で乗り切るよう励まして通常通り作業させる"
    ],
    "a": 1
  },
  {
    "idx": 953,
    "genre": 5,
    "q": "工事現場の安全標識で緑色が示す意味はどれか",
    "o": [
      "火気厳禁や立入禁止などの禁止事項を示す",
      "高電圧や段差などへの注意喚起を示す",
      "保護具着用や通行方向などの指示事項を示す",
      "安全な状態・救護設備・避難経路の案内を示す"
    ],
    "a": 3
  },
  {
    "idx": 954,
    "genre": 5,
    "q": "現場で使う「養生」という言葉の意味はどれか",
    "o": [
      "仕上げ面や周辺を汚れ・傷から保護すること",
      "作業員の体調を整えるために休養を取ること",
      "搬入した材料を倉庫に保管して在庫管理すること",
      "施工図面を現場用に拡大して描き直すこと"
    ],
    "a": 0
  },
  {
    "idx": 955,
    "genre": 5,
    "q": "ISO9001が定める品質マネジメントシステムの基本的な考え方はどれか",
    "o": [
      "品質は最終段階の検査によって確保するものとする",
      "プロセスを管理することで品質を継続的に改善する",
      "品質は個人の技量と経験に依存するものとする",
      "品質管理の仕組みは組織の規模を問わず不要とする"
    ],
    "a": 1
  },
  {
    "idx": 957,
    "genre": 5,
    "q": "「ダイバーシティ（多様性）マネジメント」の目的はどれか",
    "o": [
      "全員を同じ価値観にそろえて組織の統一性を高める",
      "女性の比率だけを高めて数値目標を達成する",
      "外国人の雇用を制限して文化の均質性を維持する",
      "多様な人材の能力を活かしてチームの成果を高める"
    ],
    "a": 3
  },
  {
    "idx": 958,
    "genre": 5,
    "q": "熟練者から若手への技術継承で最も効果的な方法はどれか",
    "o": [
      "作業マニュアルだけを渡して自主学習に委ねる",
      "座学での座学講習のみで技術の理論を教える",
      "熟練者の作業を遠くから見て自ら体得させる",
      "言語化しながら実演し若手が実践してフィードバックを受けるサイクルを繰り返す"
    ],
    "a": 3
  },
  {
    "idx": 960,
    "genre": 5,
    "q": "「BCP（事業継続計画）」の目的はどれか",
    "o": [
      "災害等の緊急事態でも事業を継続または早期復旧するため",
      "経営合理化のために人員を削減して固定費を圧縮するため",
      "既存事業の利益率を最大化して株主への配当を増やすため",
      "新規事業の立ち上げに向けた市場調査と計画策定のため"
    ],
    "a": 0
  },
  {
    "idx": 961,
    "genre": 5,
    "q": "工事写真の撮影で最も重要なことはどれか",
    "o": [
      "構図や画角を工夫して美しい写真に仕上げること",
      "何を・いつ・どの段階で撮影したかが明確にわかること",
      "できるだけ大量に撮影して記録漏れを防ぐこと",
      "作業員の作業風景を含めて撮影して現場の雰囲気を記録すること"
    ],
    "a": 1
  },
  {
    "idx": 963,
    "genre": 5,
    "q": "工事現場における「KYT（危険予知トレーニング）」と「KY活動」の違いはどれか",
    "o": [
      "両者は名称が異なるだけで内容は全く同じものである",
      "KYTは教育・訓練の手法でKY活動は実際の作業前に行う実践活動",
      "KYTは現場で行う簡易な確認でKY活動は教室で行う座学研修",
      "KY活動は法律で義務付けられておらず実施は任意である"
    ],
    "a": 1
  },
  {
    "idx": 965,
    "genre": 5,
    "q": "現場のトイレや休憩所の設置基準を定めている法律はどれか",
    "o": [
      "労働安全衛生法に基づく事務所衛生基準規則で定められている",
      "道路法に基づく道路占用許可の条件として定められている",
      "消防法に基づく防火管理者の業務の一つとして定められている",
      "建築基準法に基づく建築物の用途規制として定められている"
    ],
    "a": 0
  },
  {
    "idx": 966,
    "genre": 5,
    "q": "「見える化」の目的として最も正しいものはどれか",
    "o": [
      "都合の悪い情報を隠して良い結果だけを報告すること",
      "作業場所の見た目をきれいにして来客時の印象を良くすること",
      "問題・情報を視覚的に共有し誰でも状況を把握できるようにすること",
      "監視カメラを設置して作業員の行動を常時記録すること"
    ],
    "a": 2
  },
  {
    "idx": 973,
    "genre": 5,
    "q": "現場で「ヒヤリハット」を報告しやすくするために最も重要なことはどれか",
    "o": [
      "報告書の書式を複雑にして詳細な情報を求めること",
      "報告者を責めない文化（ノーブレーム文化）を作ること",
      "報告を義務化して未報告に罰則を設けること",
      "報告件数に応じて個人の人事評価に反映すること"
    ],
    "a": 1
  },
  {
    "idx": 976,
    "genre": 5,
    "q": "工事現場でのコミュニケーションで「確認の復唱」が重要な理由はどれか",
    "o": [
      "復唱することで時間を稼ぎ次の作業の段取りを考えるため",
      "復唱によって相手の発言を疑っていることを明示するため",
      "現場での慣例として形式的なマナーにすぎないため",
      "聞き間違いや認識のズレを防ぎ正確な情報伝達を確保するため"
    ],
    "a": 3
  },
  {
    "idx": 977,
    "genre": 5,
    "q": "現場での「安全パトロール」の目的はどれか",
    "o": [
      "事務所内の書類や帳票類のみを確認して記録を整備するため",
      "現場の不安全状態や不安全行動を発見し是正するため",
      "作業員を監視して規則違反者に罰則を適用するため",
      "工事の進捗状況を確認して工程遅延を報告するため"
    ],
    "a": 1
  },
  {
    "idx": 979,
    "genre": 5,
    "q": "現場のデジタルサイネージや掲示板で安全情報を共有する利点はどれか",
    "o": [
      "掲示物は作業中に確認する余裕がなく効果は限定的である",
      "管理者のみが閲覧可能なため情報の機密性が確保される",
      "紙の使用量が削減されるだけでコスト削減が主な目的である",
      "言葉の壁を越えて視覚的に安全情報を全員に伝達できる"
    ],
    "a": 3
  },
  {
    "idx": 981,
    "genre": 5,
    "q": "工事現場の防音対策で最も効果的なものはどれか",
    "o": [
      "工事の騒音は法的に規制されていないため対策は不要である",
      "近隣に迷惑がかからないよう夜間に集中して作業を行う",
      "近隣住民への事前挨拶のみで十分な対策となる",
      "低騒音型の機械使用・防音シートの設置・作業時間の配慮を組み合わせる"
    ],
    "a": 3
  },
  {
    "idx": 983,
    "genre": 5,
    "q": "現場監督が毎日つける「安全日誌」の最も重要な記載内容はどれか",
    "o": [
      "当日の天候に対する個人的な感想と体感気温を記録する",
      "当日の安全活動・危険発見・是正措置の記録を残す",
      "個人的な日記として業務以外の出来事を記録する",
      "昼食の内容と休憩時間中の過ごし方を記録する"
    ],
    "a": 1
  },
  {
    "idx": 984,
    "genre": 5,
    "q": "「リーダーシップ」と「マネジメント」の違いとして正しいものはどれか",
    "o": [
      "リーダーシップはビジョンを示し人を動かす力でマネジメントは計画的に組織を管理する力",
      "マネジメントは時代遅れの考え方であり現在の組織運営では不要となっている",
      "リーダーシップは組織に不要でありマネジメントだけがあれば十分である",
      "リーダーシップとマネジメントは表現が違うだけで全く同じ概念である"
    ],
    "a": 0
  },
  {
    "idx": 1204,
    "genre": 5,
    "q": "建設現場における「作業開始前点検」の目的はどれか",
    "o": [
      "当日の天気予報を確認して作業可否を判断するため",
      "機械・設備・安全装置の異常を事前に発見し事故を防止するため",
      "作業員の出勤状況を確認して欠員がないか把握するため",
      "当日の工事費用の支出予定を確認して予算管理するため"
    ],
    "a": 1
  },
  {
    "idx": 1228,
    "genre": 5,
    "q": "建設業における「施工体系図」の掲示が必要なのはどれか",
    "o": [
      "個人住宅のリフォーム工事のみに限定される",
      "公共工事及び民間工事のうち下請負契約の総額が一定額以上のもの",
      "元請のみで施工し下請を使わない工事に必要となる",
      "工事の金額に関わらず全ての建設工事に必要となる"
    ],
    "a": 1
  },
  {
    "idx": 1234,
    "genre": 5,
    "q": "「品質管理」と「品質保証」の違いとして正しいものはどれか",
    "o": [
      "品質保証は組織内の自主的な活動であり顧客への説明は不要",
      "品質管理は製造過程の管理で品質保証は顧客に品質を保証する活動",
      "品質管理と品質保証は名称が異なるだけで同じ内容の活動",
      "品質管理は品質保証を包含するより広い範囲の概念である"
    ],
    "a": 1
  },
  {
    "idx": 1235,
    "genre": 5,
    "q": "建設現場での「リスク」の定義として正しいものはどれか",
    "o": [
      "危険の発生確率と被害の大きさの組合せで評価する",
      "安全でない状態を意味する安全の対義語である",
      "事故が実際に起きた後の被害結果のことである",
      "作業環境に存在する危険要因そのものを指す"
    ],
    "a": 0
  },
  {
    "idx": 1332,
    "genre": 5,
    "q": "建設現場で「ヒヤリハット報告」を行う目的として最も適切なものはどれか？",
    "o": [
      "作業班の活動成果を上司に報告して評価を得るため",
      "提出された報告書の件数を管理して統計資料を作成するため",
      "事故が起きる前に危険要因を把握し予防するため",
      "報告者の安全意識の欠如を指摘して注意喚起するため"
    ],
    "a": 2
  },
  {
    "idx": 1442,
    "genre": 5,
    "q": "名刺交換の際、相手の名刺を受け取ったときの正しい対応はどれか？",
    "o": [
      "受け取った名刺はすぐにポケットにしまって紛失を防ぐ",
      "名刺入れの上に置き打ち合わせ中はテーブルに並べておく",
      "相手の連絡先を忘れないうちに名刺の裏にメモを書き込む",
      "かさばらないよう名刺を折り曲げて財布に入れる"
    ],
    "a": 1
  },
  {
    "idx": 1444,
    "genre": 5,
    "q": "ビジネスメールで「CC」に入れる人の役割として正しいものはどれか？",
    "o": [
      "メールの内容について返信の義務がある主たる宛先",
      "情報共有として内容を知っておくべき関係者",
      "メールの内容を最終的に承認する決裁権限者",
      "メールを第三者に転送する際の中継先となる人"
    ],
    "a": 1
  },
  {
    "idx": 1448,
    "genre": 5,
    "q": "建設現場での「指差し呼称」の目的として正しいものはどれか？",
    "o": [
      "大きな声を出す発声練習の機会として活用するため",
      "確認の意識を高めてヒューマンエラーを防止するため",
      "指や手の柔軟性を維持するための運動として行うため",
      "周囲の作業員に自分の作業内容を見せて共有するため"
    ],
    "a": 1
  },
  {
    "idx": 1450,
    "genre": 5,
    "q": "来客を応接室に案内する際、ドアの開け方として正しいものはどれか？",
    "o": [
      "来客自身にドアを開けてもらい案内者は後から入室する",
      "内開きの場合は自分が先に入室しドアを押さえて来客を招き入れる",
      "来客の後ろからドアを押して来客を先に入室させる",
      "ドアを開けたら来客より先に着席して待つ"
    ],
    "a": 1
  },
  {
    "idx": 1462,
    "genre": 5,
    "q": "ビジネスメールの件名として適切なものはどれか？",
    "o": [
      "「お疲れ様です」のみを件名として記載する",
      "「大事なお話がございます」と抽象的に記載する",
      "「こんにちは」と日常の挨拶を件名に記載する",
      "「【ご確認依頼】3月15日工程会議の議事録」と具体的に記載する"
    ],
    "a": 3
  },
  {
    "idx": 1480,
    "genre": 5,
    "q": "ビジネスにおける「リスクアセスメント」の意味として正しいものはどれか？",
    "o": [
      "将来の売上や利益の予測値を算出する業務分析手法",
      "顧客の満足度を定量的に調査して改善点を抽出する手法",
      "従業員の業績を評価して処遇に反映する人事評価制度",
      "危険性を特定して評価し対策を決定する一連のプロセス"
    ],
    "a": 3
  },
  {
    "idx": 1488,
    "genre": 5,
    "q": "建設現場の「整理整頓」の「整理」と「整頓」の違いとして正しいものはどれか？",
    "o": [
      "整理は作業場所を掃除すること、整頓は物品を飾ること",
      "整理は作業内容を記録すること、整頓は記録を保管すること",
      "整理と整頓は表現が違うだけで実質的に同じ意味を持つ",
      "整理は不要なものを捨てること、整頓は必要なものを使いやすく配置すること"
    ],
    "a": 3
  },
  {
    "idx": 2404,
    "genre": 5,
    "q": "建設現場で初めて会う協力会社の作業員に挨拶する際、最も適切な対応はどれか",
    "o": [
      "「おはようございます」と声をかけ自分の名前と所属を伝える",
      "相手の視線を確認してから無言で軽く会釈する",
      "作業が全て終わってから挨拶を交わすようにする",
      "自分から挨拶はせず相手から声をかけられるのを待つ"
    ],
    "a": 0
  },
  {
    "idx": 2406,
    "genre": 5,
    "q": "工事現場で来客（施主）を案内する際、最も適切な対応はどれか",
    "o": [
      "来客より先に歩いて進行方向の安全を確認しながら案内する",
      "来客の後ろを歩いて来客自身に行き先を選んでもらう",
      "案内は他の作業員に任せて自分は通常の業務に戻る",
      "来客にヘルメット等の保護具を用意し危険箇所を説明してから案内する"
    ],
    "a": 3
  },
  {
    "idx": 2408,
    "genre": 5,
    "q": "建設現場での安全朝礼で、作業員が最も注意すべき確認事項はどれか",
    "o": [
      "当日の作業内容と危険ポイントの確認を行う",
      "当日の天気予報と気温の変化を確認する",
      "昼食の手配と休憩場所の確認を行う",
      "退勤時間と翌日の出勤時間を確認する"
    ],
    "a": 0
  },
  {
    "idx": 2414,
    "genre": 5,
    "q": "工事現場での「ヒヤリ・ハット」活動の目的はどれか",
    "o": [
      "事故に至らなかった危険事例を共有して再発を防止する",
      "事故発生後の責任の所在を明らかにして再発防止策を立てる",
      "作業員の安全意識を個別に評価して人事考課に反映する",
      "報告件数に応じた罰則を設けて安全意識の低い作業員を特定する"
    ],
    "a": 0
  },
  {
    "idx": 2428,
    "genre": 5,
    "q": "建設業でよく使われる「施主（せしゅ）」の意味として正しいものはどれか",
    "o": [
      "工事を発注する建物の持ち主や注文者を指す",
      "工事を実際に施工する元請の建設会社を指す",
      "工事の品質や安全を監督する現場監督者を指す",
      "設計図書を作成して確認申請を行う建築士を指す"
    ],
    "a": 0
  },
  {
    "idx": 2433,
    "genre": 5,
    "q": "「進捗（しんちょく）」の意味として正しいものはどれか。（例：「工事の進捗状況を報告する」）",
    "o": [
      "物事が進み行くこと・はかどること",
      "工事の施工品質や仕上がりの良さを指す",
      "工事にかかった費用の総額を指す",
      "工事中に発生した問題点や課題を指す"
    ],
    "a": 0
  }
]